[
  {
    "cluster": "modalidade",
    "categoria": "corrida",
    "keyword": "creatina gummy para corrida"
  },
  {
    "cluster": "modalidade",
    "categoria": "crossfit",
    "keyword": "creatina gummy para crossfit"
  },
  {
    "cluster": "modalidade",
    "categoria": "futebol",
    "keyword": "creatina gummy para futebol"
  },
  {
    "cluster": "modalidade",
    "categoria": "ciclismo",
    "keyword": "creatina gummy para ciclismo"
  },
  {
    "cluster": "modalidade",
    "categoria": "natacao",
    "keyword": "creatina gummy para natacao"
  },
  {
    "cluster": "objetivo",
    "categoria": "academia",
    "keyword": "creatina gummy para academia"
  },
  {
    "cluster": "objetivo",
    "categoria": "musculacao",
    "keyword": "creatina gummy para musculacao"
  },
  {
    "cluster": "objetivo",
    "categoria": "hipertrofia",
    "keyword": "creatina gummy para hipertrofia"
  },
  {
    "cluster": "objetivo",
    "categoria": "treino funcional",
    "keyword": "creatina gummy para treino funcional"
  },
  {
    "cluster": "publico",
    "categoria": "mulheres",
    "keyword": "creatina gummy para mulheres"
  }
]
